<?xml version="1.0" encoding="utf-8"?>
<odoo>
    <record id="as_sale_report_view_pivot" model="ir.ui.view">
        <field name="name">sale.report.search.inherit</field>
        <field name="model">sale.report</field>
        <field name="inherit_id" ref="sale.view_order_product_search" />
        <field name="arch" type="xml">
            <data>
                <xpath expr="//field[@name='partner_id']" position="after">
                    <field name="as_laboratorio" />
                    <field name="as_line_product" />
                </xpath>
            </data>
        </field>
    </record>

</odoo>